groupBMC/__init__.py
groupBMC/groupBMC.py
groupBMC-1.0.dist-info/LICENSE
groupBMC-1.0.dist-info/METADATA
groupBMC-1.0.dist-info/WHEEL
groupBMC-1.0.dist-info/top_level.txt
groupBMC-1.0.dist-info/RECORD
