Metadata-Version: 2.1
Name: groupBMC
Version: 1.0
Summary: Bayesian Model Comparison for Group Studies
Home-page: https://github.com/cpilab/group-bayesian-model-comparison.git
Author: Sichao Yang
Author-email: sichao@cs.wisc.edu
License: UNKNOWN
Platform: UNKNOWN
License-File: LICENSE
